{"0": {"Date": " Nov 4, 2017", "Summary": "\"Cashier\"", "Pros": "Fun and interesting and really cool", "Cons": "Long hours and average pay"}, "1": {"Date": " Dec 10, 2017", "Summary": "\"cant live your life\"", "Pros": "They are always hiring .", "Cons": "Never recommended for my friends and family"}, "2": {"Date": " Dec 10, 2017", "Summary": "\"I hate this place\"", "Pros": "The pay is so bad here.", "Cons": "The pay here is horrible and not liveable"}, "3": {"Date": " Nov 19, 2017", "Summary": "\"Manager\"", "Pros": "Job. Lively. Days has the crew.", "Cons": "Upper management. Pay. Schedules. Day off never existed"}, "4": {"Date": " Nov 20, 2017", "Summary": "\"Cashier\"", "Pros": "Good starting Job for teens", "Cons": "Poor ManagmentThey hire almost anyoneNo team work"}, "5": {"Date": " Nov 4, 2017", "Summary": "\"great first job\"", "Pros": "free food, uniforms, nice management", "Cons": "bad customers but overall ok"}, "6": {"Date": " Nov 4, 2017", "Summary": "\"Okay\"", "Pros": "It was the best to learn a fast paced job", "Cons": "A lot of work and customers a"}, "7": {"Date": " Nov 5, 2017", "Summary": "\"Cook\"", "Pros": "I really like my job at Mcdonalds in Liberty tx. I have been working here and work the grill overnight. I luv it i wouldn't give it up 4 no thing else right.", "Cons": "We really need 2 work together."}, "8": {"Date": " Nov 3, 2017", "Summary": "\"Great Company Culture\"", "Pros": "Very Family Focused, Great Benefits, Flexible Work Time, Nice Vacation and Holidays", "Cons": "Lots of work, More than full time effots"}, "9": {"Date": " Nov 4, 2017", "Summary": "\"My time at McDonald\u2019s\"", "Pros": "Good burgers and free soda for employees", "Cons": "Greasy floors and ate too many hamburgers"}}