{"0": {"Date": " Feb 3, 2017", "Summary": "\"Great Place\"", "Pros": "I liked working with people and the job itself.", "Cons": "The pay was a little low but acceptable for the work."}, "1": {"Date": " Feb 3, 2017", "Summary": "\"love to cook\"", "Pros": "team work i will make the best out of bad situtions", "Cons": "nothing i work well with others"}, "2": {"Date": " Mar 10, 2017", "Summary": "\"Cashier\"", "Pros": "We eat for free. No limitations as long as we are on break from our scheduled shift. Sometimes it's a fun place to work.", "Cons": "Poor pay. My manager has had many questionable encounters with young girl employees. It's public knowledge so much so a manager of a medical retail establishment bought it up to me in conversation."}, "3": {"Date": " Mar 11, 2017", "Summary": "\"Cook fryer back drive thru\"", "Pros": "Easy work, laid back, easy training,", "Cons": "Not enough hours, better for high school students."}, "4": {"Date": " Feb 2, 2017", "Summary": "\"Crew Member\"", "Pros": "Hours are always available so that you may have a nice paycheck.", "Cons": "Lack of structure in the work place as far as levels of management."}, "5": {"Date": " Feb 2, 2017", "Summary": "\"Cashier\"", "Pros": "Nice work environment and whatever", "Cons": "Only got minimum wage of course"}, "6": {"Date": " Feb 3, 2017", "Summary": "\"Pretty fun\"", "Pros": "That it was a fast paced job, Something new everyday,", "Cons": "Some managers and fellow crew workers were less than ideal."}, "7": {"Date": " Feb 16, 2017", "Summary": "\"It's what you'd expect\"", "Pros": "Easy work, managers are usually relaxed", "Cons": "low pay, lack of growth, rude customers"}, "8": {"Date": " Feb 16, 2017", "Summary": "\"Good High School job\"", "Pros": "They gave me flexible hours", "Cons": "Opportunities are limited in a way"}, "9": {"Date": " Feb 1, 2017", "Summary": "\"Great\"", "Pros": "Good money and very fun.", "Cons": "There was not a lot of business."}}