{"0": {"Date": " Oct 24, 2017", "Summary": "\"Nothing exciting\"", "Pros": "Meeting new people almost every month", "Cons": "Terrible time management and poor conditions"}, "1": {"Date": " Oct 25, 2017", "Summary": "\"sucked\"", "Pros": "fast days. time went by fast there", "Cons": "overall bad staff and no room to move up"}, "2": {"Date": " Oct 25, 2017", "Summary": "\"Abusive work environment\"", "Pros": "Learning experience and certain opportunities.", "Cons": "Power hunger bosses, customer is always right, expendable employees and constant verbal abuse"}, "3": {"Date": " Oct 9, 2017", "Summary": "\"Kids night!!\"", "Pros": "Fun activities with lots of cookies and activities for children. Painting, coloring and reading children's coloring books!!!", "Cons": "More staff needed in the restaurant"}, "4": {"Date": " Oct 10, 2017", "Summary": "\"Good\"", "Pros": "Benefits are potentiality really good.", "Cons": "Long hours24 hour stores"}, "5": {"Date": " Oct 23, 2017", "Summary": "\"Okay job\"", "Pros": "not a long term career", "Cons": "low paying job not too exciting"}, "6": {"Date": " Oct 23, 2017", "Summary": "\"Poor\"", "Pros": "Discount food and fine workers", "Cons": "Blows and its hot af"}, "7": {"Date": " Oct 24, 2017", "Summary": "\"Current service staff\"", "Pros": "lenient schedule which is helpful around my school schedule", "Cons": "The environment is negative to be in"}, "8": {"Date": " Oct 8, 2017", "Summary": "\"General manager\"", "Pros": "Great benefits Awesome vacation great 401k", "Cons": "no life Late shifts Must find a Corporation Not a franchise"}, "9": {"Date": " Oct 9, 2017", "Summary": "\"Cashier/money taker/opener\"", "Pros": "Love my job! Only bad part are grumpy customers", "Cons": "Love workers and the owner is a great man"}}