{"0": {"Date": " Oct 20, 2017", "Summary": "\"Absolute bad experience\"", "Pros": "Was able to get hours.", "Cons": "Played with your moneyManagement didn\u2019t careEmployees were unprofessionalThe place it self was negative"}, "1": {"Date": " Sep 28, 2017", "Summary": "\"Overnight manager\"", "Pros": "Free food held me down because the pay was so low", "Cons": "Long hours, bad pay. Free food was unhealthy tho"}, "2": {"Date": " Sep 29, 2017", "Summary": "\"Greets customers, take orders\"", "Pros": "Nothing is positive about it.", "Cons": "Needs better management and pay."}, "3": {"Date": " Sep 13, 2017", "Summary": "\"Cashier\"", "Pros": "Great place to improve customer service skills.", "Cons": "The pay could be better"}, "4": {"Date": " Sep 13, 2017", "Summary": "\"Good first job\"", "Pros": "Nice people and managers", "Cons": "Can get a little hectic during peak hours"}, "5": {"Date": " Sep 13, 2017", "Summary": "\"Nice one\"", "Pros": "\"It is very good company having good work culture and employee friendly policies.\"", "Cons": "Nothing to say......... overall is good"}, "6": {"Date": " Sep 27, 2017", "Summary": "\"McDonald's\"", "Pros": "It's a great way to get job experience if you don't have any", "Cons": "If you work at a McDonald's located near a college campus, you'll have to deal with drunk customers."}, "7": {"Date": " Sep 27, 2017", "Summary": "\"Good for a first job..That's it.\"", "Pros": "McDonald's offers a flexible schedule", "Cons": "Low pay rate and the customers treat you like crap even in management."}, "8": {"Date": " Sep 28, 2017", "Summary": "\"Part time associate\"", "Pros": "Flexible hours and acceptable working environment.", "Cons": "You have to deal with unpleasant customers"}, "9": {"Date": " Sep 13, 2017", "Summary": "\"janitor\"", "Pros": "really easy to work with", "Cons": "none i could think of"}}