{"0": {"Date": " May 11, 2016", "Summary": "\"Cashier\"", "Pros": "It was fast pased and easy work", "Cons": "There was none everything was great"}, "1": {"Date": " May 11, 2016", "Summary": "\"Cashier\"", "Pros": "Meet nice peopleFree mealsDecent schedule accommodation", "Cons": "Rude customersUnreliable managementChildish rude employees"}, "2": {"Date": " May 24, 2016", "Summary": "\"Cashier\"", "Pros": "The workflow is adequate in general, and once and a while you get to have breaks. You also receive good benefits.", "Cons": "You may have frequent run-ins with the janitor who may often have to come out to ask you if there are items such as toilet or soap supplied in the stock room."}, "3": {"Date": " May 24, 2016", "Summary": "\"Shift Manager\"", "Pros": "Great experience in managing all ranges of employees.", "Cons": "Very low pay and benefits for amount of work expected."}, "4": {"Date": " May 24, 2016", "Summary": "\"Fry cook\"", "Pros": "Easy job, friendly management and staff, open ears, willing to help, fun environment , free meals if worked full shift", "Cons": "Slow days, low hours, t shirt, expensive, rarely received raises, room for improvement"}, "5": {"Date": " May 25, 2016", "Summary": "\"Good\"", "Pros": "Ok place to work good hours", "Cons": "Staffing upper management, cleanliness broken equipment"}, "6": {"Date": " May 25, 2016", "Summary": "\"Cashier\"", "Pros": "Cashier and food service is easy to learn.", "Cons": "I wanted to work more hours than what they were willing to offer."}, "7": {"Date": " May 9, 2016", "Summary": "\"Manager\"", "Pros": "Great customer skills and smile.", "Cons": "Not very fast sometimes overnight due to busy times."}, "8": {"Date": " May 9, 2016", "Summary": "\"Pretty Good\"", "Pros": "The food is great and good", "Cons": "The place gets dirty sometimes"}, "9": {"Date": " May 10, 2016", "Summary": "\"Manager\"", "Pros": "Sometimes sometimes bad sometimes so so Fun", "Cons": "Company is very very Hard"}}