{"0": {"Date": " Jan 13, 2017", "Summary": "\"Great culture, change on the horizon\"", "Pros": "Over the last 10 years, relatively stable. good management team", "Cons": "Over the last 1 1/2 there have been various restructuring efforts. Political environment became more of a factor."}, "1": {"Date": " Jan 27, 2017", "Summary": "\"cashier\"", "Pros": "lots of hours available to work", "Cons": "low wages below poverty level"}, "2": {"Date": " Jan 27, 2017", "Summary": "\"Great\"", "Pros": "awesome burgers for lunch and dinner", "Cons": "bad customers to deal with everyday"}, "3": {"Date": " Jan 27, 2017", "Summary": "\"Good first job, but gets old fast\"", "Pros": "- learn how to deal with customers- fast paced environment- makes you mature fast- great first job", "Cons": "- gets old fast- way better jobs out there- high turnover"}, "4": {"Date": " Jan 28, 2017", "Summary": "\"Front end cashier\"", "Pros": "Interesting clients. Customer contact.", "Cons": "Rude customers who complain trying to get free food"}, "5": {"Date": " Jan 12, 2017", "Summary": "\"managment\"", "Pros": "the $ is good. love the bonuses and the crew.", "Cons": "hours can be hard if you are not able to do them."}, "6": {"Date": " Jan 26, 2017", "Summary": "\"Waitress\"", "Pros": "Great tips, easy job, decent hours", "Cons": "terrible, management did not work well with employees"}, "7": {"Date": " Feb 17, 2017", "Summary": "\"worse job\"", "Pros": "have great benefits50% off food", "Cons": "working hard for $7.25never happy"}, "8": {"Date": " Jan 27, 2017", "Summary": "\"Meh\"", "Pros": "Hours are flexible and can work around school and other events.Easy job to acquire and after a couple weeks it is relatively easy to keep up", "Cons": "Managers and crew are in and out so no real stability in the restaurant. Pay starts at 8.25 and lower for people who aren't necessarily legal from what I have heard. Raises are every 6 months and can range from nothing to .25 $ based in performance, but ultimately raises are based off management. Scheduling can be a bit off especially if you ask for time off you may get a whole week off after requesting only one day off."}, "9": {"Date": " Jan 12, 2017", "Summary": "\"Shift manager review\"", "Pros": "People, good management, friendly environment.", "Cons": "Not flexible, long hours, low pay"}}